swn/__init__.py
swn/_version.py
swn/compat.py
swn/core.py
swn/file.py
swn/logger.py
swn/spatial.py
swn/util.py
swn/modflow/__init__.py
swn/modflow/_base.py
swn/modflow/_misc.py
swn/modflow/_modelplot.py
swn/modflow/_swnmf6.py
swn/modflow/_swnmodflow.py
surface_water_network-0.8.dist-info/METADATA
surface_water_network-0.8.dist-info/WHEEL
surface_water_network-0.8.dist-info/licenses/LICENSE
surface_water_network-0.8.dist-info/RECORD
