Metadata-Version: 2.3
Name: surface-water-network
Version: 0.8
Summary: Surface water network
Project-URL: Documentation, https://mwtoews.github.io/surface-water-network/
Project-URL: Source, https://github.com/mwtoews/surface-water-network
Author-email: Mike Taves <mwtoews@gmail.com>, Brioch Hemmings <briochh@gmail.com>
Maintainer-email: Mike Taves <mwtoews@gmail.com>
License: BSD 3-Clause
License-File: LICENSE
Keywords: MODFLOW,flopy,groundwater,surface water
Classifier: Development Status :: 4 - Beta
Classifier: Intended Audience :: Science/Research
Classifier: License :: OSI Approved :: BSD License
Classifier: Operating System :: OS Independent
Classifier: Programming Language :: Python
Classifier: Programming Language :: Python :: 3 :: Only
Classifier: Topic :: Scientific/Engineering :: Hydrology
Requires-Python: >=3.8
Requires-Dist: geopandas>=0.9
Requires-Dist: packaging
Requires-Dist: pandas>=1.2
Requires-Dist: pyproj>=2.2
Requires-Dist: rtree
Requires-Dist: shapely
Provides-Extra: dev
Requires-Dist: flopy>=3.3.6; extra == 'dev'
Requires-Dist: ipython; extra == 'dev'
Requires-Dist: matplotlib; extra == 'dev'
Requires-Dist: netcdf4; extra == 'dev'
Requires-Dist: numpydoc; extra == 'dev'
Requires-Dist: pydata-sphinx-theme; extra == 'dev'
Requires-Dist: pytest-cov; extra == 'dev'
Requires-Dist: pytest-xdist; extra == 'dev'
Requires-Dist: pytest>=3.3; extra == 'dev'
Requires-Dist: sphinx-issues; extra == 'dev'
Requires-Dist: sphinx<6; extra == 'dev'
Provides-Extra: doc
Requires-Dist: ipython; extra == 'doc'
Requires-Dist: matplotlib; extra == 'doc'
Requires-Dist: numpydoc; extra == 'doc'
Requires-Dist: pydata-sphinx-theme; extra == 'doc'
Requires-Dist: sphinx-issues; extra == 'doc'
Requires-Dist: sphinx<6; extra == 'doc'
Provides-Extra: extra
Requires-Dist: flopy>=3.3.6; extra == 'extra'
Requires-Dist: matplotlib; extra == 'extra'
Requires-Dist: netcdf4; extra == 'extra'
Provides-Extra: test
Requires-Dist: pytest-cov; extra == 'test'
Requires-Dist: pytest-xdist; extra == 'test'
Requires-Dist: pytest>=3.3; extra == 'test'
